{
	"name": "pipeline1",
	"properties": {
		"activities": [
			{
				"name": "Copy data1",
				"type": "Copy",
				"dependsOn": [],
				"policy": {
					"timeout": "0.12:00:00",
					"retry": 0,
					"retryIntervalInSeconds": 30,
					"secureOutput": false,
					"secureInput": false
				},
				"userProperties": [],
				"typeProperties": {
					"source": {
						"type": "DelimitedTextSource",
						"storeSettings": {
							"type": "AzureBlobFSReadSettings",
							"recursive": true,
							"enablePartitionDiscovery": false
						},
						"formatSettings": {
							"type": "DelimitedTextReadSettings"
						}
					},
					"sink": {
						"type": "ParquetSink",
						"storeSettings": {
							"type": "AzureBlobFSWriteSettings"
						},
						"formatSettings": {
							"type": "ParquetWriteSettings"
						}
					},
					"enableStaging": false,
					"parallelCopies": 8,
					"logSettings": {
						"enableCopyActivityLog": true,
						"copyActivityLogSettings": {
							"logLevel": "Info",
							"enableReliableLogging": false
						},
						"logLocationSettings": {
							"linkedServiceName": {
								"referenceName": "onprem2cloud_alt",
								"type": "LinkedServiceReference",
								"parameters": {
									"strg_act_nm": "https://onprem2cloud.dfs.core.windows.net"
								}
							},
							"path": "landing2silver/customer"
						}
					},
					"dataIntegrationUnits": 4,
					"translator": {
						"type": "TabularTranslator",
						"mappings": [
							{
								"source": {
									"name": "CustomerID",
									"type": "String",
									"physicalType": "String"
								},
								"sink": {
									"name": "CustomerID",
									"type": "String",
									"physicalType": "UTF8"
								}
							},
							{
								"source": {
									"name": "FirstName",
									"type": "String",
									"physicalType": "String"
								},
								"sink": {
									"name": "FirstName",
									"type": "String",
									"physicalType": "UTF8"
								}
							},
							{
								"source": {
									"name": "LastName",
									"type": "String",
									"physicalType": "String"
								},
								"sink": {
									"name": "LastName",
									"type": "String",
									"physicalType": "UTF8"
								}
							},
							{
								"source": {
									"name": "Email",
									"type": "String",
									"physicalType": "String"
								},
								"sink": {
									"name": "Email",
									"type": "String",
									"physicalType": "UTF8"
								}
							},
							{
								"source": {
									"name": "PhoneNumber",
									"type": "String",
									"physicalType": "String"
								},
								"sink": {
									"name": "PhoneNumber",
									"type": "String",
									"physicalType": "UTF8"
								}
							},
							{
								"source": {
									"name": "DateOfBirth",
									"type": "String",
									"physicalType": "String"
								},
								"sink": {
									"name": "DateOfBirth",
									"type": "String",
									"physicalType": "UTF8"
								}
							},
							{
								"source": {
									"name": "JoinDate",
									"type": "String",
									"physicalType": "String"
								},
								"sink": {
									"name": "JoinDate",
									"type": "String",
									"physicalType": "UTF8"
								}
							}
						],
						"typeConversion": true,
						"typeConversionSettings": {
							"allowDataTruncation": true,
							"treatBooleanAsNumber": false
						}
					}
				},
				"inputs": [
					{
						"referenceName": "crm",
						"type": "DatasetReference",
						"parameters": {
							"CONTAINER_NM": "landingzone",
							"DIRECTORY_NM": "customer"
						}
					}
				],
				"outputs": [
					{
						"referenceName": "Parquet1",
						"type": "DatasetReference",
						"parameters": {
							"CONTAINER_NM": "silver",
							"DIR_NM": {
								"value": "@concat('customer/',formatDateTime(utcNow(),'yyyy-MM-dd'))",
								"type": "Expression"
							}
						}
					}
				]
			}
		],
		"annotations": []
	}
}